{
    "dependencies": ["."],
    "graphs": {
        "agent": "./src/agents/main.py:agent",
        "simple": "./src/agents/simple.py:agent",
        "rag" : "./src/agents/rag.py:agent",
        "code_review" : "./src/agents/code_review.py:agent",
        "react" : "./src/agents/react.py:agent",
        "evaluator" : "./src/agents/evaluator.py:agent",
        "orchestrator" : "./src/agents/orchestrator.py:agent",
        "orchestrator_docs" : "./src/agents/orchestrator_doc.py:orchestrator_worker",
        "support" : "./src/agents/support/agent.py:agent",
        "booking" : "./src/agents/support/nodes/booking/node.py:booking_node"
    },
    "env": ".env"
}